{
  "photos": [
    {
      "id": 1,
      "photoUrl": "http://gmm.fc.utm.my/~jumail/photos/photo1.jpg",
      "thumbUrl": "http://gmm.fc.utm.my/~jumail/preview/photo1.jpg",
      "like": 0,
      "dislike": 0,
      "allowReset": 1,
      "allowDuplicate": 0
    },
    {
      "id": 2,
      "photoUrl": "http://gmm.fc.utm.my/~jumail/photos/photo2.jpg",
      "thumbUrl": "http://gmm.fc.utm.my/~jumail/preview/photo2.jpg",
      "like": 8,
      "dislike": 8,
      "allowReset": 0,
      "allowDuplicate": 0
    },
    {
      "id": 3,
      "photoUrl": "http://gmm.fc.utm.my/~jumail/photos/photo3.jpg",
      "thumbUrl": "http://gmm.fc.utm.my/~jumail/preview/photo3.jpg",
      "like": 4,
      "dislike": 1,
      "allowReset": 0,
      "allowDuplicate": 1
    },
    {
      "id": 4,
      "photoUrl": "http://gmm.fc.utm.my/~jumail/photos/photo4.jpg",
      "thumbUrl": "http://gmm.fc.utm.my/~jumail/preview/photo4.jpg",
      "like": 2,
      "dislike": 2,
      "allowReset": 1,
      "allowDuplicate": 0
    },
    {
      "id": 5,
      "photoUrl": "http://gmm.fc.utm.my/~jumail/photos/photo5.jpg",
      "thumbUrl": "http://gmm.fc.utm.my/~jumail/preview/photo5.jpg",
      "like": 3,
      "dislike": 2,
      "allowReset": 1,
      "allowDuplicate": 1
    },
    {
      "photoUrl": "http://gmm.fc.utm.my/~jumail/photos/photo1.jpg",
      "thumbUrl": "http://gmm.fc.utm.my/~jumail/preview/photo1.jpg",
      "id": 6
    },
    {
      "id": 7,
      "photoUrl": "http://gmm.fc.utm.my/~jumail/photos/photo1.jpg",
      "thumbUrl": "http://gmm.fc.utm.my/~jumail/preview/photo1.jpg",
      "like": 0,
      "dislike": 0,
      "allowReset": 0,
      "allowDuplicate": 0
    },
    {
      "id": 8,
      "photoUrl": "http://gmm.fc.utm.my/~jumail/photos/photo5.jpg",
      "thumbUrl": "http://gmm.fc.utm.my/~jumail/preview/photo5.jpg",
      "like": 1,
      "dislike": 0,
      "allowReset": 0,
      "allowDuplicate": 0
    },
    {
      "id": 9,
      "photoUrl": "http://gmm.fc.utm.my/~jumail/photos/photo3.jpg",
      "thumbUrl": "http://gmm.fc.utm.my/~jumail/preview/photo3.jpg",
      "like": 0,
      "dislike": 0,
      "allowReset": 0,
      "allowDuplicate": 0
    },
    {
      "id": 10,
      "photoUrl": "http://gmm.fc.utm.my/~jumail/photos/photo3.jpg",
      "thumbUrl": "http://gmm.fc.utm.my/~jumail/preview/photo3.jpg",
      "like": 0,
      "dislike": 0,
      "allowReset": 0,
      "allowDuplicate": 0
    },
    {
      "id": 11,
      "photoUrl": "http://gmm.fc.utm.my/~jumail/photos/photo3.jpg",
      "thumbUrl": "http://gmm.fc.utm.my/~jumail/preview/photo3.jpg",
      "like": 0,
      "dislike": 0,
      "allowReset": 0,
      "allowDuplicate": 0
    }
  ]
}